fc_xd_bigdata.py
fc_bigdatr-1.0.dist-info/METADATA
fc_bigdatr-1.0.dist-info/WHEEL
fc_bigdatr-1.0.dist-info/top_level.txt
fc_bigdatr-1.0.dist-info/RECORD
