Metadata-Version: 2.1
Name: fc-bigdatr
Version: 1.0
Summary: 数据3
Home-page: UNKNOWN
Author: wzdr
Author-email: 3233175474@qq.com
License: UNKNOWN
Platform: UNKNOWN
